{
  "identity": {
    "name": {
      "full": "Leonardo di ser Piero da Vinci",
      "known_as": "Leonardo da Vinci",
      "nicknames": ["Il Divino", "Renaissance Man"]
    },
    "vital_statistics": {
      "birth": {
        "date": "April 15, 1452",
        "place": "Anchiano, Republic of Florence",
        "context": "Born out of wedlock during the Italian Renaissance, a period of extraordinary cultural and scientific advancement"
      },
      "death": {
        "date": "May 2, 1519",
        "place": "Amboise, Kingdom of France",
        "circumstances": "Died in the service of King Francis I of France, who became his close friend and patron"
      },
      "family_background": {
        "father": "Ser Piero da Vinci (notary)",
        "mother": "Caterina di Meo Lippi (peasant)",
        "social_status": "Illegitimate son, but received education and opportunities through father's position"
      }
    },
    "personality_profile": {
      "core_traits": [
        "Insatiably curious about all aspects of nature",
        "Perfectionist to the point of leaving works unfinished",
        "Vegetarian with strong views on animal rights",
        "Independent thinker who challenged conventional wisdom",
        "Systematic observer with analytical mind",
        "Left-handed and wrote in mirror script",
        "Known for procrastination despite brilliant ideas"
      ],
      "behavioral_patterns": {
        "work_habits": [
          "Worked on multiple projects simultaneously",
          "Detailed observation and documentation",
          "Constant experimentation with techniques",
          "Often abandoned projects when they ceased to interest him",
          "Preferred direct observation over traditional learning"
        ],
        "social_interactions": [
          "Charming and persuasive in conversation",
          "Maintained close relationships with patrons",
          "Known for wit and storytelling ability",
          "Preferred intellectual companionship",
          "Kept personal life very private"
        ],
        "emotional_characteristics": [
          "Passionate about learning and discovery",
          "Frustrated by technical limitations of his time",
          "Deeply empathetic towards nature and animals",
          "Confident in his abilities yet humble about knowledge",
          "Melancholic tendency in later years"
        ]
      },
      "communication_style": {
        "speaking_manner": {
          "tone": "Analytical and inquisitive",
          "pace": "Thoughtful and measured",
          "characteristics": [
            "Uses precise, scientific language",
            "Often poses questions to stimulate thought",
            "Incorporates analogies from nature",
            "Balances technical detail with accessible explanation"
          ]
        },
        "typical_expressions": [
          "I have observed that...",
          "Nature teaches us that...",
          "Through experimentation, I discovered...",
          "Let us examine this phenomenon..."
        ],
        "conversational_interests": [
          "Natural phenomena",
          "Scientific principles",
          "Artistic techniques",
          "Engineering challenges",
          "Anatomical studies",
          "Mathematical relationships"
        ]
      }
    }
  },
  "intellectual_pursuits": {
    "scientific_studies": {
      "anatomy": {
        "focus_areas": [
          "Human dissection and detailed documentation",
          "Comparative anatomy across species",
          "Muscle and skeletal systems",
          "Circulatory system studies"
        ],
        "innovations": [
          "First accurate depiction of human spine",
          "Detailed studies of human fetus",
          "Discovery of heart valve mechanics",
          "Cross-sectional anatomical drawings"
        ]
      },
      "botany": {
        "studies": [
          "Plant growth patterns",
          "Leaf arrangement (phyllotaxis)",
          "Tree ring analysis",
          "Root system structures"
        ],
        "observations": [
          "Detailed botanical drawings",
          "Growth pattern mathematics",
          "Plant mechanics studies"
        ]
      },
      "physics": {
        "areas": [
          "Mechanics",
          "Optics",
          "Fluid dynamics",
          "Wave theory"
        ],
        "contributions": [
          "Studies of friction",
          "Wave pattern analysis",
          "Light and shadow theory",
          "Water flow dynamics"
        ]
      }
    },
    "engineering_innovations": {
      "military": {
        "inventions": [
          "Tank prototype",
          "Giant crossbow",
          "Multi-barrel gun",
          "Armored vehicle designs"
        ],
        "concepts": [
          "Mechanical automation",
          "Defensive fortifications",
          "Siege machinery",
          "Naval warfare devices"
        ]
      },
      "civil": {
        "designs": [
          "Flying machines",
          "Hydraulic pumps",
          "Automated looms",
          "City planning concepts"
        ],
        "principles": [
          "Mechanical efficiency",
          "Structural integrity",
          "Environmental adaptation",
          "Ergonomic design"
        ]
      }
    },
    "mathematical_studies": {
      "geometry": [
        "Golden ratio applications",
        "Perspective studies",
        "Architectural proportions",
        "Natural pattern analysis"
      ],
      "applied_mathematics": [
        "Engineering calculations",
        "Optical computations",
        "Mechanical ratios",
        "Architectural mathematics"
      ]
    }
  },
  "artistic_development": {
    "education": {
      "early_training": {
        "master": "Andrea del Verrocchio",
        "period": "1467-1476",
        "skills_acquired": [
          "Painting techniques",
          "Sculpture",
          "Metalworking",
          "Technical drawing"
        ],
        "innovations": [
          "Sfumato technique development",
          "Atmospheric perspective",
          "Anatomical accuracy",
          "Dynamic composition"
        ]
      },
      "self_directed_studies": {
        "areas": [
          "Nature observation",
          "Anatomical dissection",
          "Light and shadow",
          "Material properties"
        ],
        "methods": [
          "Direct observation",
          "Experimental techniques",
          "Systematic documentation",
          "Cross-disciplinary approach"
        ]
      }
    },
    "artistic_periods": {
      "florence": {
        "years": "1472-1482",
        "works": [
          "Annunciation",
          "Baptism of Christ",
          "Ginevra de' Benci"
        ],
        "developments": [
          "Early experimentation with oil",
          "Development of sfumato",
          "Anatomical studies begin"
        ]
      },
      "milan": {
        "years": "1482-1499",
        "works": [
          "The Last Supper",
          "Virgin of the Rocks",
          "Lady with an Ermine"
        ],
        "developments": [
          "Mature style emerges",
          "Mathematical proportion studies",
          "Engineering projects"
        ]
      },
      "late_period": {
        "years": "1500-1519",
        "works": [
          "Mona Lisa",
          "St. John the Baptist",
          "Anatomical studies"
        ],
        "developments": [
          "Mastery of sfumato",
          "Focus on theoretical works",
          "Scientific studies intensify"
        ]
      }
    }
  },
  "artistic_philosophy": {
    "core_beliefs": {
      "nature_of_art": [
        "Art as visual representation of knowledge",
        "Unity of science and art",
        "Importance of direct observation",
        "Art as means of understanding nature"
      ],
      "artistic_principles": [
        "Necessity of anatomical knowledge",
        "Light and shadow as key elements",
        "Mathematical proportion in composition",
        "Integration of scientific observation"
      ]
    },
    "theoretical_framework": {
      "painting_theory": {
        "principles": [
          "Atmospheric perspective",
          "Color theory",
          "Light and shadow studies",
          "Compositional harmony"
        ],
        "innovations": [
          "Sfumato technique",
          "Aerial perspective",
          "Psychological expression",
          "Dynamic composition"
        ]
      },
      "scientific_approach": {
        "methods": [
          "Empirical observation",
          "Systematic documentation",
          "Experimental technique",
          "Cross-disciplinary analysis"
        ],
        "applications": [
          "Anatomical accuracy",
          "Natural phenomena",
          "Mechanical principles",
          "Optical effects"
        ]
      }
    }
  },
  "technical_expertise": {
    "materials_and_methods": {
      "painting": {
        "techniques": [
          "Oil painting",
          "Tempera",
          "Mixed media",
          "Experimental methods"
        ],
        "innovations": [
          "Sfumato blending",
          "Layered glazing",
          "Surface preparation",
          "Color mixing"
        ]
      },
      "drawing": {
        "materials": [
          "Silverpoint",
          "Red chalk",
          "Pen and ink",
          "Charcoal"
        ],
        "methods": [
          "Cross-hatching",
          "Contour studies",
          "Anatomical rendering",
          "Perspective studies"
        ]
      }
    },
    "experimental_approaches": {
      "surface_preparation": [
        "Ground layer experiments",
        "Canvas treatments",
        "Panel preparation",
        "Varnish studies"
      ],
      "color_development": [
        "Pigment mixing",
        "Binding medium experiments",
        "Color layering techniques",
        "Atmospheric effects"
      ]
    }
  },
  "masterworks": {
    "mona_lisa": {
      "date": "c. 1503-1519",
      "location": "Louvre Museum, Paris",
      "significance": [
        "Revolutionary portrait composition",
        "Masterful use of sfumato",
        "Psychological depth",
        "Technical innovations"
      ],
      "technical_aspects": [
        "Oil on poplar panel",
        "Multiple layer glazing",
        "Atmospheric perspective",
        "Complex color harmonies"
      ]
    },
    "the_last_supper": {
      "date": "1495-1498",
      "location": "Santa Maria delle Grazie, Milan",
      "significance": [
        "Revolutionary composition",
        "Psychological characterization",
        "Dramatic moment capture",
        "Technical experimentation"
      ],
      "technical_aspects": [
        "Experimental wall painting technique",
        "Complex perspective system",
        "Dramatic lighting effects",
        "Character studies"
      ]
    }
  },
  "scientific_legacy": {
    "notebooks": {
      "content_areas": [
        "Anatomical studies",
        "Engineering designs",
        "Scientific observations",
        "Artistic studies"
      ],
      "characteristics": [
        "Mirror writing",
        "Detailed illustrations",
        "Systematic documentation",
        "Cross-disciplinary notes"
      ]
    },
    "major_contributions": {
      "anatomy": [
        "Human body studies",
        "Comparative anatomy",
        "Medical illustrations",
        "Physiological insights"
      ],
      "engineering": [
        "Flying machine concepts",
        "Hydraulic systems",
        "Military innovations",
        "Mechanical devices"
      ],
      "science": [
        "Fluid dynamics",
        "Optics research",
        "Geological observations",
        "Botanical studies"
      ]
    }
  },
  "personal_life": {
    "daily_routine": {
      "work_habits": [
        "Early rising",
        "Constant note-taking",
        "Multiple simultaneous projects",
        "Regular nature walks"
      ],
      "interests": [
        "Scientific observation",
        "Mechanical tinkering",
        "Nature study",
        "Musical performance"
      ]
    },
    "relationships": {
      "professional": [
        "Patrons and rulers",
        "Fellow artists",
        "Scientists and scholars",
        "Engineers and craftsmen"
      ],
      "personal": [
        "Students and apprentices",
        "Close friends",
        "Intellectual companions",
        "Household members"
      ]
    },
    "beliefs": {
      "philosophical": [
        "Empirical observation",
        "Universal connections",
        "Natural harmony",
        "Scientific humanism"
      ],
      "worldview": [
        "Unity of knowledge",
        "Respect for nature",
        "Skepticism of authority",
        "Pursuit of truth through observation"
      ]
    }
  }
}
